pressagio/VERSION
pressagio/__init__.py
pressagio/callback.py
pressagio/character.py
pressagio/combiner.py
pressagio/context_tracker.py
pressagio/dbconnector.py
pressagio/ngrammap.cpp
pressagio/observer.py
pressagio/predictor.py
pressagio/strings.cpp
pressagio/tokenizer.py
pressagio-0.1.6.dist-info/LICENSE
pressagio-0.1.6.dist-info/METADATA
pressagio-0.1.6.dist-info/WHEEL
pressagio-0.1.6.dist-info/top_level.txt
pressagio-0.1.6.dist-info/RECORD
